watsappmod/__init__.py
watsappmod/send_whats_app.py
unlimited_message-0.1.dist-info/LICENSE
unlimited_message-0.1.dist-info/METADATA
unlimited_message-0.1.dist-info/WHEEL
unlimited_message-0.1.dist-info/top_level.txt
unlimited_message-0.1.dist-info/RECORD
